elm-license-finder/__init__.py
elm-license-finder/main.py
elm_license_finder/__init__.py
elm_license_finder/find_licenses.py
elm_license_finder/main.py
elm_license_finder-1.0.1.dist-info/LICENSE
elm_license_finder-1.0.1.dist-info/METADATA
elm_license_finder-1.0.1.dist-info/WHEEL
elm_license_finder-1.0.1.dist-info/top_level.txt
elm_license_finder-1.0.1.dist-info/RECORD
