Metadata-Version: 2.1
Name: elm-license-finder
Version: 1.0.1
Summary: Collects license information for Elm project dependencies.
Home-page: https://github.com/wolfadex/elm-license-finder
Author: Wolfgang Schuster
License: UNKNOWN
Platform: UNKNOWN
Classifier: Programming Language :: Python :: 3
Classifier: License :: OSI Approved :: MIT License
Classifier: Operating System :: OS Independent
Requires-Python: >=3.6
